decatenator/__init__.py
decatenator/_core.py
decatenator/cli.py
decatenator-0.1.0.dist-info/licenses/LICENSE
decatenator-0.1.0.dist-info/METADATA
decatenator-0.1.0.dist-info/WHEEL
decatenator-0.1.0.dist-info/entry_points.txt
decatenator-0.1.0.dist-info/top_level.txt
decatenator-0.1.0.dist-info/RECORD
