Metadata-Version: 2.4
Name: decatenator
Version: 0.1.0
Summary: Unpack Markdown-embedded code into real source files.
Author-email: Philip Orange <git@philiporange.com>
License: CC0 1.0 Universal
Project-URL: Source, https://github.com/philiporange/decatenator
Keywords: markdown,code
Classifier: License :: CC0 1.0 Universal (CC0 1.0) Public Domain Dedication
Classifier: Programming Language :: Python :: 3
Requires-Python: >=3.9
License-File: LICENSE
Dynamic: license-file
